{"forms":{"Nom":{"Sing":{"Masc":"αποθαμένος","Fem":"αποθαμένη","Neut":"αποθαμένο"},"Plur":{"Masc":"αποθαμένοι","Fem":"αποθαμένες","Neut":"αποθαμένα"}},"Gen":{"Sing":{"Masc":"αποθαμένου","Fem":"αποθαμένης","Neut":"αποθαμένου"},"Plur":{"Masc":"αποθαμένων","Fem":"αποθαμένων","Neut":"αποθαμένων"}},"Acc":{"Sing":{"Masc":"αποθαμένο","Fem":"αποθαμένη","Neut":"αποθαμένο"},"Plur":{"Masc":"αποθαμένους","Fem":"αποθαμένες","Neut":"αποθαμένα"}},"Voc":{"Sing":{"Masc":"αποθαμένε","Fem":"αποθαμένη","Neut":"αποθαμένο"},"Plur":{"Masc":"αποθαμένοι","Fem":"αποθαμένες","Neut":"αποθαμένα"}}}}