{"forms":{"Nom":{"Sing":{"Masc":"γαλανός","Fem":"γαλανή","Neut":"γαλανό"},"Plur":{"Masc":"γαλανοί","Fem":"γαλανές","Neut":"γαλανά"}},"Gen":{"Sing":{"Masc":"γαλανού","Fem":"γαλανής","Neut":"γαλανού"},"Plur":{"Masc":"γαλανών","Fem":"γαλανών","Neut":"γαλανών"}},"Acc":{"Sing":{"Masc":"γαλανό","Fem":"γαλανή","Neut":"γαλανό"},"Plur":{"Masc":"γαλανούς","Fem":"γαλανές","Neut":"γαλανά"}},"Voc":{"Sing":{"Masc":"γαλανέ","Fem":"γαλανή","Neut":"γαλανό"},"Plur":{"Masc":"γαλανοί","Fem":"γαλανές","Neut":"γαλανά"}}}}