{"forms":{"Nom":{"Sing":{"Masc":"υπαίθριος","Fem":"υπαίθρια","Neut":"υπαίθριο"},"Plur":{"Masc":"υπαίθριοι","Fem":"υπαίθριες","Neut":"υπαίθρια"}},"Gen":{"Sing":{"Masc":"υπαίθριου","Fem":"υπαίθριας","Neut":"υπαίθριου"},"Plur":{"Masc":"υπαίθριων","Fem":"υπαίθριων","Neut":"υπαίθριων"}},"Acc":{"Sing":{"Masc":"υπαίθριο","Fem":"υπαίθρια","Neut":"υπαίθριο"},"Plur":{"Masc":"υπαίθριους","Fem":"υπαίθριες","Neut":"υπαίθρια"}},"Voc":{"Sing":{"Masc":"υπαίθριε","Fem":"υπαίθρια","Neut":"υπαίθριο"},"Plur":{"Masc":"υπαίθριοι","Fem":"υπαίθριες","Neut":"υπαίθρια"}}}}