{"forms":{"Nom":{"Sing":{"Masc":"χάρτινος","Fem":"χάρτινη","Neut":"χάρτινο"},"Plur":{"Masc":"χάρτινοι","Fem":"χάρτινες","Neut":"χάρτινα"}},"Gen":{"Sing":{"Masc":"χάρτινου","Fem":"χάρτινης","Neut":"χάρτινου"},"Plur":{"Masc":"χάρτινων","Fem":"χάρτινων","Neut":"χάρτινων"}},"Acc":{"Sing":{"Masc":"χάρτινο","Fem":"χάρτινη","Neut":"χάρτινο"},"Plur":{"Masc":"χάρτινους","Fem":"χάρτινες","Neut":"χάρτινα"}},"Voc":{"Sing":{"Masc":"χάρτινε","Fem":"χάρτινη","Neut":"χάρτινο"},"Plur":{"Masc":"χάρτινοι","Fem":"χάρτινες","Neut":"χάρτινα"}}}}