{"forms":{"Nom":{"Sing":{"Masc":"ολυμπιακός","Fem":"ολυμπιακή","Neut":"ολυμπιακό"},"Plur":{"Masc":"ολυμπιακοί","Fem":"ολυμπιακές","Neut":"ολυμπιακά"}},"Gen":{"Sing":{"Masc":"ολυμπιακού","Fem":"ολυμπιακής","Neut":"ολυμπιακού"},"Plur":{"Masc":"ολυμπιακών","Fem":"ολυμπιακών","Neut":"ολυμπιακών"}},"Acc":{"Sing":{"Masc":"ολυμπιακό","Fem":"ολυμπιακή","Neut":"ολυμπιακό"},"Plur":{"Masc":"ολυμπιακούς","Fem":"ολυμπιακές","Neut":"ολυμπιακά"}},"Voc":{"Sing":{"Masc":"ολυμπιακέ","Fem":"ολυμπιακή","Neut":"ολυμπιακό"},"Plur":{"Masc":"ολυμπιακοί","Fem":"ολυμπιακές","Neut":"ολυμπιακά"}}}}