{"forms":{"Nom":{"Sing":{"Masc":"αγαπημένος","Fem":"αγαπημένη","Neut":"αγαπημένο"},"Plur":{"Masc":"αγαπημένοι","Fem":"αγαπημένες","Neut":"αγαπημένα"}},"Gen":{"Sing":{"Masc":"αγαπημένου","Fem":"αγαπημένης","Neut":"αγαπημένου"},"Plur":{"Masc":"αγαπημένων","Fem":"αγαπημένων","Neut":"αγαπημένων"}},"Acc":{"Sing":{"Masc":"αγαπημένο","Fem":"αγαπημένη","Neut":"αγαπημένο"},"Plur":{"Masc":"αγαπημένους","Fem":"αγαπημένες","Neut":"αγαπημένα"}},"Voc":{"Sing":{"Masc":"αγαπημένε","Fem":"αγαπημένη","Neut":"αγαπημένο"},"Plur":{"Masc":"αγαπημένοι","Fem":"αγαπημένες","Neut":"αγαπημένα"}}}}