{"forms":{"Nom":{"Sing":{"Masc":"έκπληκτος","Fem":"έκπληκτη","Neut":"έκπληκτο"},"Plur":{"Masc":"έκπληκτοι","Fem":"έκπληκτες","Neut":"έκπληκτα"}},"Gen":{"Sing":{"Masc":"έκπληκτου","Fem":"έκπληκτης","Neut":"έκπληκτου"},"Plur":{"Masc":"έκπληκτων","Fem":"έκπληκτων","Neut":"έκπληκτων"}},"Acc":{"Sing":{"Masc":"έκπληκτο","Fem":"έκπληκτη","Neut":"έκπληκτο"},"Plur":{"Masc":"έκπληκτους","Fem":"έκπληκτες","Neut":"έκπληκτα"}},"Voc":{"Sing":{"Masc":"έκπληκτε","Fem":"έκπληκτη","Neut":"έκπληκτο"},"Plur":{"Masc":"έκπληκτοι","Fem":"έκπληκτες","Neut":"έκπληκτα"}}}}