{"forms":{"Nom":{"Sing":{"Masc":"ασυνήθιστος","Fem":"ασυνήθιστη","Neut":"ασυνήθιστο"},"Plur":{"Masc":"ασυνήθιστοι","Fem":"ασυνήθιστες","Neut":"ασυνήθιστα"}},"Gen":{"Sing":{"Masc":"ασυνήθιστου","Fem":"ασυνήθιστης","Neut":"ασυνήθιστου"},"Plur":{"Masc":"ασυνήθιστων","Fem":"ασυνήθιστων","Neut":"ασυνήθιστων"}},"Acc":{"Sing":{"Masc":"ασυνήθιστο","Fem":"ασυνήθιστη","Neut":"ασυνήθιστο"},"Plur":{"Masc":"ασυνήθιστους","Fem":"ασυνήθιστες","Neut":"ασυνήθιστα"}},"Voc":{"Sing":{"Masc":"ασυνήθιστε","Fem":"ασυνήθιστη","Neut":"ασυνήθιστο"},"Plur":{"Masc":"ασυνήθιστοι","Fem":"ασυνήθιστες","Neut":"ασυνήθιστα"}}}}