{"forms":{"Nom":{"Sing":{"Masc":"βεβιασμένος","Fem":"βεβιασμένη","Neut":"βεβιασμένο"},"Plur":{"Masc":"βεβιασμένοι","Fem":"βεβιασμένες","Neut":"βεβιασμένα"}},"Gen":{"Sing":{"Masc":"βεβιασμένου","Fem":"βεβιασμένης","Neut":"βεβιασμένου"},"Plur":{"Masc":"βεβιασμένων","Fem":"βεβιασμένων","Neut":"βεβιασμένων"}},"Acc":{"Sing":{"Masc":"βεβιασμένο","Fem":"βεβιασμένη","Neut":"βεβιασμένο"},"Plur":{"Masc":"βεβιασμένους","Fem":"βεβιασμένες","Neut":"βεβιασμένα"}},"Voc":{"Sing":{"Masc":"βεβιασμένε","Fem":"βεβιασμένη","Neut":"βεβιασμένο"},"Plur":{"Masc":"βεβιασμένοι","Fem":"βεβιασμένες","Neut":"βεβιασμένα"}}}}