{"forms":{"Nom":{"Sing":{"Masc":"επισκευασμένος","Fem":"επισκευασμένη","Neut":"επισκευασμένο"},"Plur":{"Masc":"επισκευασμένοι","Fem":"επισκευασμένες","Neut":"επισκευασμένα"}},"Gen":{"Sing":{"Masc":"επισκευασμένου","Fem":"επισκευασμένης","Neut":"επισκευασμένου"},"Plur":{"Masc":"επισκευασμένων","Fem":"επισκευασμένων","Neut":"επισκευασμένων"}},"Acc":{"Sing":{"Masc":"επισκευασμένο","Fem":"επισκευασμένη","Neut":"επισκευασμένο"},"Plur":{"Masc":"επισκευασμένους","Fem":"επισκευασμένες","Neut":"επισκευασμένα"}},"Voc":{"Sing":{"Masc":"επισκευασμένε","Fem":"επισκευασμένη","Neut":"επισκευασμένο"},"Plur":{"Masc":"επισκευασμένοι","Fem":"επισκευασμένες","Neut":"επισκευασμένα"}}}}