{"forms":{"Nom":{"Sing":{"Masc":"ευχόμενος","Fem":"ευχόμενη","Neut":"ευχόμενο"},"Plur":{"Masc":"ευχόμενοι","Fem":"ευχόμενες","Neut":"ευχόμενα"}},"Gen":{"Sing":{"Masc":"ευχόμενου","Fem":"ευχόμενης","Neut":"ευχόμενου"},"Plur":{"Masc":"ευχόμενων","Fem":"ευχόμενων","Neut":"ευχόμενων"}},"Acc":{"Sing":{"Masc":"ευχόμενο","Fem":"ευχόμενη","Neut":"ευχόμενο"},"Plur":{"Masc":"ευχόμενους","Fem":"ευχόμενες","Neut":"ευχόμενα"}},"Voc":{"Sing":{"Masc":"ευχόμενε","Fem":"ευχόμενη","Neut":"ευχόμενο"},"Plur":{"Masc":"ευχόμενοι","Fem":"ευχόμενες","Neut":"ευχόμενα"}}}}