{"forms":{"Nom":{"Sing":{"Masc":"μελετημένος","Fem":"μελετημένη","Neut":"μελετημένο"},"Plur":{"Masc":"μελετημένοι","Fem":"μελετημένες","Neut":"μελετημένα"}},"Gen":{"Sing":{"Masc":"μελετημένου","Fem":"μελετημένης","Neut":"μελετημένου"},"Plur":{"Masc":"μελετημένων","Fem":"μελετημένων","Neut":"μελετημένων"}},"Acc":{"Sing":{"Masc":"μελετημένο","Fem":"μελετημένη","Neut":"μελετημένο"},"Plur":{"Masc":"μελετημένους","Fem":"μελετημένες","Neut":"μελετημένα"}},"Voc":{"Sing":{"Masc":"μελετημένε","Fem":"μελετημένη","Neut":"μελετημένο"},"Plur":{"Masc":"μελετημένοι","Fem":"μελετημένες","Neut":"μελετημένα"}}}}