{"forms":{"Nom":{"Sing":{"Masc":"συγκεκριμένος","Fem":"συγκεκριμένη","Neut":"συγκεκριμένο"},"Plur":{"Masc":"συγκεκριμένοι","Fem":"συγκεκριμένες","Neut":"συγκεκριμένα"}},"Gen":{"Sing":{"Masc":"συγκεκριμένου","Fem":"συγκεκριμένης","Neut":"συγκεκριμένου"},"Plur":{"Masc":"συγκεκριμένων","Fem":"συγκεκριμένων","Neut":"συγκεκριμένων"}},"Acc":{"Sing":{"Masc":"συγκεκριμένο","Fem":"συγκεκριμένη","Neut":"συγκεκριμένο"},"Plur":{"Masc":"συγκεκριμένους","Fem":"συγκεκριμένες","Neut":"συγκεκριμένα"}},"Voc":{"Sing":{"Masc":"συγκεκριμένε","Fem":"συγκεκριμένη","Neut":"συγκεκριμένο"},"Plur":{"Masc":"συγκεκριμένοι","Fem":"συγκεκριμένες","Neut":"συγκεκριμένα"}}}}