{"forms":{"Nom":{"Sing":{"Masc":"επισκεπτόμενος","Fem":"επισκεπτόμενη","Neut":"επισκεπτόμενο"},"Plur":{"Masc":"επισκεπτόμενοι","Fem":"επισκεπτόμενες","Neut":"επισκεπτόμενα"}},"Gen":{"Sing":{"Masc":"επισκεπτόμενου","Fem":"επισκεπτόμενης","Neut":"επισκεπτόμενου"},"Plur":{"Masc":"επισκεπτόμενων","Fem":"επισκεπτόμενων","Neut":"επισκεπτόμενων"}},"Acc":{"Sing":{"Masc":"επισκεπτόμενο","Fem":"επισκεπτόμενη","Neut":"επισκεπτόμενο"},"Plur":{"Masc":"επισκεπτόμενους","Fem":"επισκεπτόμενες","Neut":"επισκεπτόμενα"}},"Voc":{"Sing":{"Masc":"επισκεπτόμενε","Fem":"επισκεπτόμενη","Neut":"επισκεπτόμενο"},"Plur":{"Masc":"επισκεπτόμενοι","Fem":"επισκεπτόμενες","Neut":"επισκεπτόμενα"}}}}