{"forms":{"Nom":{"Sing":{"Masc":"παραγγελμένος","Fem":"παραγγελμένη","Neut":"παραγγελμένο"},"Plur":{"Masc":"παραγγελμένοι","Fem":"παραγγελμένες","Neut":"παραγγελμένα"}},"Gen":{"Sing":{"Masc":"παραγγελμένου","Fem":"παραγγελμένης","Neut":"παραγγελμένου"},"Plur":{"Masc":"παραγγελμένων","Fem":"παραγγελμένων","Neut":"παραγγελμένων"}},"Acc":{"Sing":{"Masc":"παραγγελμένο","Fem":"παραγγελμένη","Neut":"παραγγελμένο"},"Plur":{"Masc":"παραγγελμένους","Fem":"παραγγελμένες","Neut":"παραγγελμένα"}},"Voc":{"Sing":{"Masc":"παραγγελμένε","Fem":"παραγγελμένη","Neut":"παραγγελμένο"},"Plur":{"Masc":"παραγγελμένοι","Fem":"παραγγελμένες","Neut":"παραγγελμένα"}}}}