{"forms":{"Nom":{"Sing":{"Masc":"πατρικός","Fem":"πατρική","Neut":"πατρικό"},"Plur":{"Masc":"πατρικοί","Fem":"πατρικές","Neut":"πατρικά"}},"Gen":{"Sing":{"Masc":"πατρικού","Fem":"πατρικής","Neut":"πατρικού"},"Plur":{"Masc":"πατρικών","Fem":"πατρικών","Neut":"πατρικών"}},"Acc":{"Sing":{"Masc":"πατρικό","Fem":"πατρική","Neut":"πατρικό"},"Plur":{"Masc":"πατρικούς","Fem":"πατρικές","Neut":"πατρικά"}},"Voc":{"Sing":{"Masc":"πατρικέ","Fem":"πατρική","Neut":"πατρικό"},"Plur":{"Masc":"πατρικοί","Fem":"πατρικές","Neut":"πατρικά"}}}}