{"forms":{"Nom":{"Sing":{"Masc":"πλαστικός","Fem":"πλαστική","Neut":"πλαστικό"},"Plur":{"Masc":"πλαστικοί","Fem":"πλαστικές","Neut":"πλαστικά"}},"Gen":{"Sing":{"Masc":"πλαστικού","Fem":"πλαστικής","Neut":"πλαστικού"},"Plur":{"Masc":"πλαστικών","Fem":"πλαστικών","Neut":"πλαστικών"}},"Acc":{"Sing":{"Masc":"πλαστικό","Fem":"πλαστική","Neut":"πλαστικό"},"Plur":{"Masc":"πλαστικούς","Fem":"πλαστικές","Neut":"πλαστικά"}},"Voc":{"Sing":{"Masc":"πλαστικέ","Fem":"πλαστική","Neut":"πλαστικό"},"Plur":{"Masc":"πλαστικοί","Fem":"πλαστικές","Neut":"πλαστικά"}}}}