{"forms":{"Nom":{"Sing":{"Masc":"ρυθμισμένος","Fem":"ρυθμισμένη","Neut":"ρυθμισμένο"},"Plur":{"Masc":"ρυθμισμένοι","Fem":"ρυθμισμένες","Neut":"ρυθμισμένα"}},"Gen":{"Sing":{"Masc":"ρυθμισμένου","Fem":"ρυθμισμένης","Neut":"ρυθμισμένου"},"Plur":{"Masc":"ρυθμισμένων","Fem":"ρυθμισμένων","Neut":"ρυθμισμένων"}},"Acc":{"Sing":{"Masc":"ρυθμισμένο","Fem":"ρυθμισμένη","Neut":"ρυθμισμένο"},"Plur":{"Masc":"ρυθμισμένους","Fem":"ρυθμισμένες","Neut":"ρυθμισμένα"}},"Voc":{"Sing":{"Masc":"ρυθμισμένε","Fem":"ρυθμισμένη","Neut":"ρυθμισμένο"},"Plur":{"Masc":"ρυθμισμένοι","Fem":"ρυθμισμένες","Neut":"ρυθμισμένα"}}}}