{"forms":{"Nom":{"Sing":{"Masc":"τωρινός","Fem":"τωρινή","Neut":"τωρινό"},"Plur":{"Masc":"τωρινοί","Fem":"τωρινές","Neut":"τωρινά"}},"Gen":{"Sing":{"Masc":"τωρινού","Fem":"τωρινής","Neut":"τωρινού"},"Plur":{"Masc":"τωρινών","Fem":"τωρινών","Neut":"τωρινών"}},"Acc":{"Sing":{"Masc":"τωρινό","Fem":"τωρινή","Neut":"τωρινό"},"Plur":{"Masc":"τωρινούς","Fem":"τωρινές","Neut":"τωρινά"}},"Voc":{"Sing":{"Masc":"τωρινέ","Fem":"τωρινή","Neut":"τωρινό"},"Plur":{"Masc":"τωρινοί","Fem":"τωρινές","Neut":"τωρινά"}}}}