{"forms":{"Nom":{"Sing":{"Masc":"φωτισμένος","Fem":"φωτισμένη","Neut":"φωτισμένο"},"Plur":{"Masc":"φωτισμένοι","Fem":"φωτισμένες","Neut":"φωτισμένα"}},"Gen":{"Sing":{"Masc":"φωτισμένου","Fem":"φωτισμένης","Neut":"φωτισμένου"},"Plur":{"Masc":"φωτισμένων","Fem":"φωτισμένων","Neut":"φωτισμένων"}},"Acc":{"Sing":{"Masc":"φωτισμένο","Fem":"φωτισμένη","Neut":"φωτισμένο"},"Plur":{"Masc":"φωτισμένους","Fem":"φωτισμένες","Neut":"φωτισμένα"}},"Voc":{"Sing":{"Masc":"φωτισμένε","Fem":"φωτισμένη","Neut":"φωτισμένο"},"Plur":{"Masc":"φωτισμένοι","Fem":"φωτισμένες","Neut":"φωτισμένα"}}}}