{"forms":{"Nom":{"Sing":{"Masc":"ψυχιατρικός","Fem":"ψυχιατρική","Neut":"ψυχιατρικό"},"Plur":{"Masc":"ψυχιατρικοί","Fem":"ψυχιατρικές","Neut":"ψυχιατρικά"}},"Gen":{"Sing":{"Masc":"ψυχιατρικού","Fem":"ψυχιατρικής","Neut":"ψυχιατρικού"},"Plur":{"Masc":"ψυχιατρικών","Fem":"ψυχιατρικών","Neut":"ψυχιατρικών"}},"Acc":{"Sing":{"Masc":"ψυχιατρικό","Fem":"ψυχιατρική","Neut":"ψυχιατρικό"},"Plur":{"Masc":"ψυχιατρικούς","Fem":"ψυχιατρικές","Neut":"ψυχιατρικά"}},"Voc":{"Sing":{"Masc":"ψυχιατρικέ","Fem":"ψυχιατρική","Neut":"ψυχιατρικό"},"Plur":{"Masc":"ψυχιατρικοί","Fem":"ψυχιατρικές","Neut":"ψυχιατρικά"}}}}