{"forms":{"Nom":{"Sing":{"Masc":"επιλεγμένος","Fem":"επιλεγμένη","Neut":"επιλεγμένο"},"Plur":{"Masc":"επιλεγμένοι","Fem":"επιλεγμένες","Neut":"επιλεγμένα"}},"Gen":{"Sing":{"Masc":"επιλεγμένου","Fem":"επιλεγμένης","Neut":"επιλεγμένου"},"Plur":{"Masc":"επιλεγμένων","Fem":"επιλεγμένων","Neut":"επιλεγμένων"}},"Acc":{"Sing":{"Masc":"επιλεγμένο","Fem":"επιλεγμένη","Neut":"επιλεγμένο"},"Plur":{"Masc":"επιλεγμένους","Fem":"επιλεγμένες","Neut":"επιλεγμένα"}},"Voc":{"Sing":{"Masc":"επιλεγμένε","Fem":"επιλεγμένη","Neut":"επιλεγμένο"},"Plur":{"Masc":"επιλεγμένοι","Fem":"επιλεγμένες","Neut":"επιλεγμένα"}}}}