{"forms":{"Nom":{"Sing":{"Masc":"εκπληγμένος","Fem":"εκπληγμένη","Neut":"εκπληγμένο"},"Plur":{"Masc":"εκπληγμένοι","Fem":"εκπληγμένες","Neut":"εκπληγμένα"}},"Gen":{"Sing":{"Masc":"εκπληγμένου","Fem":"εκπληγμένης","Neut":"εκπληγμένου"},"Plur":{"Masc":"εκπληγμένων","Fem":"εκπληγμένων","Neut":"εκπληγμένων"}},"Acc":{"Sing":{"Masc":"εκπληγμένο","Fem":"εκπληγμένη","Neut":"εκπληγμένο"},"Plur":{"Masc":"εκπληγμένους","Fem":"εκπληγμένες","Neut":"εκπληγμένα"}},"Voc":{"Sing":{"Masc":"εκπληγμένε","Fem":"εκπληγμένη","Neut":"εκπληγμένο"},"Plur":{"Masc":"εκπληγμένοι","Fem":"εκπληγμένες","Neut":"εκπληγμένα"}}}}