{"forms":{"Nom":{"Sing":{"Masc":"επαναφερμένος","Fem":"επαναφερμένη","Neut":"επαναφερμένο"},"Plur":{"Masc":"επαναφερμένοι","Fem":"επαναφερμένες","Neut":"επαναφερμένα"}},"Gen":{"Sing":{"Masc":"επαναφερμένου","Fem":"επαναφερμένης","Neut":"επαναφερμένου"},"Plur":{"Masc":"επαναφερμένων","Fem":"επαναφερμένων","Neut":"επαναφερμένων"}},"Acc":{"Sing":{"Masc":"επαναφερμένο","Fem":"επαναφερμένη","Neut":"επαναφερμένο"},"Plur":{"Masc":"επαναφερμένους","Fem":"επαναφερμένες","Neut":"επαναφερμένα"}},"Voc":{"Sing":{"Masc":"επαναφερμένε","Fem":"επαναφερμένη","Neut":"επαναφερμένο"},"Plur":{"Masc":"επαναφερμένοι","Fem":"επαναφερμένες","Neut":"επαναφερμένα"}}}}