{"forms":{"Nom":{"Sing":{"Masc":"περίεργος","Fem":"περίεργη","Neut":"περίεργο"},"Plur":{"Masc":"περίεργοι","Fem":"περίεργες","Neut":"περίεργα"}},"Gen":{"Sing":{"Masc":"περίεργου","Fem":"περίεργης","Neut":"περίεργου"},"Plur":{"Masc":"περίεργων","Fem":"περίεργων","Neut":"περίεργων"}},"Acc":{"Sing":{"Masc":"περίεργο","Fem":"περίεργη","Neut":"περίεργο"},"Plur":{"Masc":"περίεργους","Fem":"περίεργες","Neut":"περίεργα"}},"Voc":{"Sing":{"Masc":"περίεργε","Fem":"περίεργη","Neut":"περίεργο"},"Plur":{"Masc":"περίεργοι","Fem":"περίεργες","Neut":"περίεργα"}}}}