{"forms":{"Nom":{"Sing":{"Masc":"χρωστημένος","Fem":"χρωστημένη","Neut":"χρωστημένο"},"Plur":{"Masc":"χρωστημένοι","Fem":"χρωστημένες","Neut":"χρωστημένα"}},"Gen":{"Sing":{"Masc":"χρωστημένου","Fem":"χρωστημένης","Neut":"χρωστημένου"},"Plur":{"Masc":"χρωστημένων","Fem":"χρωστημένων","Neut":"χρωστημένων"}},"Acc":{"Sing":{"Masc":"χρωστημένο","Fem":"χρωστημένη","Neut":"χρωστημένο"},"Plur":{"Masc":"χρωστημένους","Fem":"χρωστημένες","Neut":"χρωστημένα"}},"Voc":{"Sing":{"Masc":"χρωστημένε","Fem":"χρωστημένη","Neut":"χρωστημένο"},"Plur":{"Masc":"χρωστημένοι","Fem":"χρωστημένες","Neut":"χρωστημένα"}}}}