{"aor.future.act":{"1p":"θα γυμνάσουμε","1s":"θα γυμνάσω","2p":"θα γυμνάσετε","2s":"θα γυμνάσεις","3p":"θα γυμνάσουν","3s":"θα γυμνάσει"},"imp.act":{"2p":"γυμνάστε","2s":"γύμνασε"},"pres.act":{"1p":"γυμνάζουμε","1s":"γυμνάζω","2p":"γυμνάζετε","2s":"γυμνάζεις","3p":"γυμνάζουν","3s":"γυμνάζει"},"aor.act":{"1p":"γυμνάσαμε","1s":"γύμνασα","2p":"γυμνάσατε","2s":"γύμνασες","3p":"γυμνάσαν","3s":"γύμνασε"},"aor.future.pass":{"1p":"θα γυμναστούμε","1s":"θα γυμναστώ","2p":"θα γυμναστείτε","2s":"θα γυμναστείς","3p":"θα γυμναστούν","3s":"θα γυμναστεί"},"imp.pass":{"2p":"γυμναστείτε","2s":"γυμνάσου"},"pres.pass":{"1p":"γυμναζόμαστε","1s":"γυμνάζομαι","2p":"γυμνάζεστε","2s":"γυμνάζεσαι","3p":"γυμνάζονται","3s":"γυμνάζεται"},"aor.pass":{"1p":"γυμναστήκαμε","1s":"γυμνάστηκα","2p":"γυμναστήκατε","2s":"γυμνάστηκες","3p":"γυμνάστηκαν","3s":"γυμνάστηκε"}}