{"aor.future.act":{"1p":"θα δροσίσουμε","1s":"θα δροσίσω","2p":"θα δροσίσετε","2s":"θα δροσίσεις","3p":"θα δροσίσουν","3s":"θα δροσίσει"},"imp.act":{"2p":"δροσίστε","2s":"δρόσισε"},"pres.act":{"1p":"δροσίζουμε","1s":"δροσίζω","2p":"δροσίζετε","2s":"δροσίζεις","3p":"δροσίζουν","3s":"δροσίζει"},"aor.act":{"1p":"δροσίσαμε","1s":"δρόσισα","2p":"δροσίσατε","2s":"δρόσισες","3p":"δρόσισαν","3s":"δρόσισε"},"aor.future.pass":{"1p":"θα δροσισθούμε","1s":"θα δροσισθώ","2p":"θα δροσισθείτε","2s":"θα δροσισθείς","3p":"θα δροσισθούν","3s":"θα δροσισθεί"},"imp.pass":{"2p":"δροσισθείτε","2s":"δροσίσου"},"pres.pass":{"1p":"δροσιζόμαστε","1s":"δροσίζομαι","2p":"δροσίζεστε","2s":"δροσίζεσαι","3p":"δροσίζονται","3s":"δροσίζεται"},"aor.pass":{"1p":"δροσισθήκαμε","1s":"δροσίσθηκα","2p":"δροσισθήκατε","2s":"δροσίσθηκες","3p":"δροσίσθηκαν","3s":"δροσίσθηκε"}}