{"aor.future.act":{"1p":"θα απαγορέψουμε","1s":"θα απαγορέψω","2p":"θα απαγορέψετε","2s":"θα απαγορέψεις","3p":"θα απαγορέψουν","3s":"θα απαγορέψει"},"imp.act":{"2p":"απαγορέψτε","2s":"απαγόρευ'"},"pres.act":{"1p":"απαγορεύουμε","1s":"απαγορεύω","2p":"απαγορεύετε","2s":"απαγορεύεις","3p":"απαγορεύουν","3s":"απαγορεύει"},"aor.act":{"1p":"απαγορέψαμε","1s":"απαγόρευσα","2p":"απαγορέψατε","2s":"απαγόρευσες","3p":"απαγορεύσαν","3s":"απαγόρευσε"},"aor.future.pass":{"1p":"θα απαγορευθούμε","1s":"θα απαγορευθώ","2p":"θα απαγορευθείτε","2s":"θα απαγορευθείς","3p":"θα απαγορευθούν","3s":"θα απαγορευθεί"},"imp.pass":{"2p":"απαγορευθείτε","2s":"απαγορέψου"},"pres.pass":{"1p":"απαγορευόμαστε","1s":"απαγορεύομαι","2p":"απαγορευόσαστε","2s":"απαγορεύεσαι","3p":"απαγορεύονται","3s":"απαγορεύεται"},"aor.pass":{"1p":"απαγορευθήκαμε","1s":"απαγορεύθηκα","2p":"απαγορευθήκατε","2s":"απαγορεύθηκες","3p":"απαγορευθήκαν","3s":"απαγορεύθηκε"}}