{"aor.future.act":{"1p":"θα μαχαιρώσουμε","1s":"θα μαχαιρώσω","2p":"θα μαχαιρώσετε","2s":"θα μαχαιρώσεις","3p":"θα μαχαιρώσουνε","3s":"θα μαχαιρώσει"},"imp.act":{"2p":"μαχαιρώστε","2s":"μαχαίρωσε"},"pres.act":{"1p":"μαχαιρώνουμε","1s":"μαχαιρώνω","2p":"μαχαιρώνετε","2s":"μαχαιρώνεις","3p":"μαχαιρώνουνε","3s":"μαχαιρώνει"},"aor.act":{"1p":"μαχαιρώσαμε","1s":"μαχαίρωσα","2p":"μαχαιρώσατε","2s":"μαχαίρωσες","3p":"μαχαίρωσαν","3s":"μαχαίρωσε"},"aor.future.pass":{"1p":"θα μαχαιρωθούμε","1s":"θα μαχαιρωθώ","2p":"θα μαχαιρωθείτε","2s":"θα μαχαιρωθείς","3p":"θα μαχαιρωθούν","3s":"θα μαχαιρωθεί"},"imp.pass":{"2p":"μαχαιρωθείτε","2s":"μαχαιρώσου"},"pres.pass":{"1p":"μαχαιρωνόμαστε","1s":"μαχαιρώνομαι","2p":"μαχαιρωνόσαστε","2s":"μαχαιρώνεσαι","3p":"μαχαιρώνονται","3s":"μαχαιρώνεται"},"aor.pass":{"1p":"μαχαιρωθήκαμε","1s":"μαχαιρώθηκα","2p":"μαχαιρωθήκατε","2s":"μαχαιρώθηκες","3p":"μαχαιρωθήκανε","3s":"μαχαιρώθηκε"}}