{"aor.future.act":{"1p":"θα παθιάσουμε","1s":"θα παθιάσω","2p":"θα παθιάσετε","2s":"θα παθιάσεις","3p":"θα παθιάσουν","3s":"θα παθιάσει"},"imp.act":{"2p":"παθιάστε","2s":"πάθιασε"},"pres.act":{"1p":"παθιάζουμε","1s":"παθιάζω","2p":"παθιάζετε","2s":"παθιάζεις","3p":"παθιάζουν","3s":"παθιάζει"},"aor.act":{"1p":"παθιάσαμε","1s":"πάθιασα","2p":"παθιάσατε","2s":"πάθιασες","3p":"πάθιασαν","3s":"πάθιασε"},"aor.future.pass":{"1p":"θα παθιαστούμε","1s":"θα παθιαστώ","2p":"θα παθιαστείτε","2s":"θα παθιαστείς","3p":"θα παθιαστούν","3s":"θα παθιαστεί"},"imp.pass":{"2p":"παθιαστείτε","2s":"παθιάσου"},"pres.pass":{"1p":"παθιαζόμαστε","1s":"παθιάζομαι","2p":"παθιάζεστε","2s":"παθιάζεσαι","3p":"παθιάζονται","3s":"παθιάζεται"},"aor.pass":{"1p":"παθιαστήκαμε","1s":"παθιάστηκα","2p":"παθιαστήκατε","2s":"παθιάστηκες","3p":"παθιάστηκαν","3s":"παθιάστηκε"}}