{"aor.future.act":{"1p":"θα παρασύρουμε","1s":"θα παρασύρω","2p":"θα παρασύρετε","2s":"θα παρασύρεις","3p":"θα παρασύρουν","3s":"θα παρασύρει"},"imp.act":{"2p":"παρασύρτε","2s":"παράσυρε"},"pres.act":{"1p":"παρασύρουμε","1s":"παρασύρω","2p":"παρασύρετε","2s":"παρασύρεις","3p":"παρασύρουν","3s":"παρασύρει"},"aor.act":{"1p":"παρασύραμε","1s":"παρέσυρα","2p":"παρασύρατε","2s":"παρέσυρες","3p":"παρέσυραν","3s":"παρέσυρε"},"aor.future.pass":{"1p":"θα παρασυρθούμε","1s":"θα παρασυρθώ","2p":"θα παρασυρθείτε","2s":"θα παρασυρθείς","3p":"θα παρασυρθούν","3s":"θα παρασυρθεί"},"imp.pass":{"2p":"παρασυρθείτε","2s":"παρασύρσου"},"pres.pass":{"1p":"παρασυρόμαστε","1s":"παρασύρομαι","2p":"παρασυρόσαστε","2s":"παρασύρεσαι","3p":"παρασύρονται","3s":"παρασύρεται"},"aor.pass":{"1p":"παρασυρθήκαμε","1s":"παρασύρθηκα","2p":"παρασυρθήκατε","2s":"παρασύρθηκες","3p":"παρασυρθήκανε","3s":"παρασύρθηκε"}}