{"aor.future.act":{"1p":"θα υποστηρίξουμε","1s":"θα υποστηρίξω","2p":"θα υποστηρίξετε","2s":"θα υποστηρίξεις","3p":"θα υποστηρίξουν","3s":"θα υποστηρίξει"},"imp.act":{"2p":"υποστηρίξτε","2s":"υποστήριξε"},"pres.act":{"1p":"υποστηρίζουμε","1s":"υποστηρίζω","2p":"υποστηρίζετε","2s":"υποστηρίζεις","3p":"υποστηρίζουν","3s":"υποστηρίζει"},"aor.act":{"1p":"υποστηρίξαμε","1s":"υποστήριξα","2p":"υποστηρίξατε","2s":"υποστήριξες","3p":"υποστήριξαν","3s":"υποστήριξε"},"aor.future.pass":{"1p":"θα υποστηριχθούμε","1s":"θα υποστηριχθώ","2p":"θα υποστηριχθείτε","2s":"θα υποστηριχθείς","3p":"θα υποστηριχθούν","3s":"θα υποστηριχθεί"},"imp.pass":{"2p":"υποστηριχθείτε","2s":"υποστηρίξου"},"pres.pass":{"1p":"υποστηριζόμαστε","1s":"υποστηρίζομαι","2p":"υποστηρίζεστε","2s":"υποστηρίζεσαι","3p":"υποστηρίζονται","3s":"υποστηρίζεται"},"aor.pass":{"1p":"υποστηριχθήκαμε","1s":"υποστηρίχθηκα","2p":"υποστηριχθήκατε","2s":"υποστηρίχθηκες","3p":"υποστηρίχθηκαν","3s":"υποστηρίχθηκε"}}