{"aor.future.act":{"1p":"θα προετοιμάσουμε","1s":"θα προετοιμάσω","2p":"θα προετοιμάσετε","2s":"θα προετοιμάσεις","3p":"θα προετοιμάσουν","3s":"θα προετοιμάσει"},"imp.act":{"2p":"προετοιμάστε","2s":"προετοίμασε"},"pres.act":{"1p":"προετοιμάζουμε","1s":"προετοιμάζω","2p":"προετοιμάζετε","2s":"προετοιμάζεις","3p":"προετοιμάζουν","3s":"προετοιμάζει"},"aor.act":{"1p":"προετοιμάσαμε","1s":"προετοίμασα","2p":"προετοιμάσατε","2s":"προετοίμασες","3p":"προετοίμασαν","3s":"προετοίμασε"},"aor.future.pass":{"1p":"θα προετοιμαστούμε","1s":"θα προετοιμαστώ","2p":"θα προετοιμαστείτε","2s":"θα προετοιμαστείς","3p":"θα προετοιμαστούν","3s":"θα προετοιμαστεί"},"imp.pass":{"2p":"προετοιμαστείτε","2s":"προετοιμάσου"},"pres.pass":{"1p":"προετοιμαζόμαστε","1s":"προετοιμάζομαι","2p":"προετοιμάζεστε","2s":"προετοιμάζεσαι","3p":"προετοιμάζονται","3s":"προετοιμάζεται"},"aor.pass":{"1p":"προετοιμαστήκαμε","1s":"προετοιμάστηκα","2p":"προετοιμαστήκατε","2s":"προετοιμάστηκες","3p":"προετοιμάστηκαν","3s":"προετοιμάστηκε"}}